<?xml version="1.0" encoding="utf-8" ?>
<dwsync>
<file name="class.html2text.php" server="C:/wamp/www/email-send/" local="130494166000000000" remote="130494166000000000" Dst="-1" />
<file name="EasyPeasyICS.php" server="C:/wamp/www/email-send/" local="130494166000000000" remote="130494166000000000" Dst="-1" />
<file name="htmlfilter.php" server="C:/wamp/www/email-send/" local="130494166000000000" remote="130494166000000000" Dst="-1" />
<file name="ntlm_sasl_client.php" server="C:/wamp/www/email-send/" local="130494166000000000" remote="130494166000000000" Dst="-1" />
<file name="class.html2text.php" server="D:/wamp/www/" local="130528884386564932" remote="130528884380000000" Dst="-1" />
<file name="EasyPeasyICS.php" server="D:/wamp/www/" local="130528884386454926" remote="130528884380000000" Dst="-1" />
<file name="htmlfilter.php" server="D:/wamp/www/" local="130528884386694940" remote="130528884380000000" Dst="-1" />
<file name="ntlm_sasl_client.php" server="D:/wamp/www/" local="130528884386704940" remote="130528884380000000" Dst="-1" />
<file name="EasyPeasyICS.php" server="C:/wamp/www/twd07-smart-pixels/" local="130525075967843260" remote="130525075960000000" Dst="2" />
<file name="class.html2text.php" server="C:/wamp/www/twd07-smart-pixels/" local="130525075968023260" remote="130525075960000000" Dst="2" />
<file name="htmlfilter.php" server="C:/wamp/www/twd07-smart-pixels/" local="130525075968103250" remote="130525075960000000" Dst="2" />
<file name="ntlm_sasl_client.php" server="C:/wamp/www/twd07-smart-pixels/" local="130525075968183260" remote="130525075960000000" Dst="2" />
</dwsync>